abstra_cli/__init__.py
abstra_cli/checkers.py
abstra_cli/cli.py
abstra_cli/credentials.py
abstra_cli/decorators.py
abstra_cli/deploy.py
abstra_cli/login.py
abstra_cli/messages.py
abstra_cli/apis/__init__.py
abstra_cli/apis/billing.py
abstra_cli/apis/dashes.py
abstra_cli/apis/files.py
abstra_cli/apis/forms.py
abstra_cli/apis/hooks.py
abstra_cli/apis/jobs.py
abstra_cli/apis/main.py
abstra_cli/apis/memberships.py
abstra_cli/apis/packages.py
abstra_cli/apis/public.py
abstra_cli/apis/subdomains.py
abstra_cli/apis/vars.py
abstra_cli/apis/workspaces.py
abstra_cli/resources/__init__.py
abstra_cli/resources/dashes.py
abstra_cli/resources/files.py
abstra_cli/resources/forms.py
abstra_cli/resources/hooks.py
abstra_cli/resources/jobs.py
abstra_cli/resources/packages.py
abstra_cli/resources/resources.py
abstra_cli/resources/subdomains.py
abstra_cli/resources/vars.py
abstra_cli/resources/workspaces.py
abstra_cli/utils/__init__.py
abstra_cli/utils/dash.py
abstra_cli/utils/file.py
abstra_cli/utils/main.py
abstra_cli-0.26.0.dist-info/METADATA
abstra_cli-0.26.0.dist-info/WHEEL
abstra_cli-0.26.0.dist-info/entry_points.txt
abstra_cli-0.26.0.dist-info/top_level.txt
abstra_cli-0.26.0.dist-info/RECORD
