Metadata-Version: 2.1
Name: abstra-cli
Version: 0.26.0
Summary: Abstra CLI
Home-page: https://github.com/abstra-app/abstra-cli
License: MIT
Platform: UNKNOWN
Requires-Dist: setuptools
Requires-Dist: websocket-client
Requires-Dist: requests
Requires-Dist: progress
Requires-Dist: crontab
Requires-Dist: colour
Requires-Dist: fire
